BPGR.py
COPYING
COPYRIGHT
MANIFEST
Makefile
README.txt
ez_setup.py
gui.py
nodes.pth
setup.py
test.py
Nodes.egg-info/PKG-INFO
Nodes.egg-info/SOURCES.txt
Nodes.egg-info/dependency_links.txt
Nodes.egg-info/entry_points.txt
Nodes.egg-info/requires.txt
Nodes.egg-info/top_level.txt
doc/Makefile
doc/README.rst
doc/conf.py
doc/contents.rst
doc/core.rst
doc/globs.rst
doc/index.rst
doc/logo.jpg
guipics/bird.png
guipics/bird.svg
guipics/cancelbutton.png
guipics/cancelbutton.svg
guipics/glider.png
guipics/glider.svg
guipics/okbutton.png
guipics/okbutton.svg
guipics/plane.png
guipics/plane.svg
guipics/rocket.png
guipics/rocket.svg
guipics/ufo.png
guipics/ufo.svg
guipics/unknown.png
guipics/unknown.svg
locale/ru/LC_MESSAGES/BPGR.mo
locale/ru/LC_MESSAGES/BPGR.po
nodes/__init__.py
nodes/__version__.py
nodes/basic.py
nodes/construct.py
nodes/core.py
nodes/globs.py
nodes/inspector.py
nodes/logger.py
nodes/logic.py
nodes/psycoptima.py
nodes/sigmoids.py
nodes/twist.py
nodes/varios.py
nodes/knots/errors.py
nodes/knots/juicer.py
nodes/stacker/__init__.py
nodes/stacker/connect.py
nodes/stacker/types.py
rfNEAT/__init__.py
rfNEAT/chromosome.py
rfNEAT/config.py
rfNEAT/genome.py
rfNEAT/population.py
rfNEAT/rands.py
rfNEAT/species.py
rfNEAT/visualize.py
rfNEAT/ctrnn/__init__.py
rfNEAT/ctrnn/ctrnn_cpp.py
rfNEAT/ctrnn/ctrnn_pure.py
rfNEAT/ifnn/__init__.py
rfNEAT/ifnn/ifnn.cpp
rfNEAT/ifnn/ifnn_pure.py
rfNEAT/ifnn/neuron.hpp
rfNEAT/ifnn/synapse.hpp
rfNEAT/iznn/__init__.py
rfNEAT/iznn/iznn.cpp
rfNEAT/iznn/iznn_pure.py
rfNEAT/iznn/network.py
rfNEAT/iznn/neuron.hpp
rfNEAT/iznn/synapse.hpp
rfNEAT/nn/__init__.py
rfNEAT/nn/nn_cpp.py
rfNEAT/nn/nn_pure.py
rfNEAT/nn/nn_cpp/ANN.cpp
rfNEAT/nn/nn_cpp/ANN.h
rfNEAT/nn/nn_cpp/PyANN.cpp
rfNEAT/nn/nn_cpp/PyANN.hpp
rfNEAT/nn/nn_cpp/example.py
rfNEAT/nn/nn_cpp/setup.py