Metadata-Version: 1.0
Name: Nodes
Version: 1.2
Summary: Neuralnets-based Artificial Intelligence implementation
Home-page: UNKNOWN
Author: Alexander Sedov aka Electronic from Lomy.RU
Author-email: Elec.Lomy.RU@gmail.com
License: UNKNOWN
Platform: UNKNOWN
Classifier: Development Status :: 5 - Production/Stable
Classifier: License :: OSI Approved :: GNU General Public License (GPL)
Classifier: Intended Audience :: Developers
Classifier: Programming Language :: Python
Classifier: Topic :: Scientific/Engineering :: Artificial Intelligence
Classifier: Topic :: Software Development :: Libraries :: Python Modules
